otx_misp/__init__.py
otx_misp/__init__.py.bak
otx_misp/__main__.py
otx_misp/cli.py
otx_misp/configuration.py
otx_misp/configuration.py.bak
otx_misp/otx/.gitignore
otx_misp/otx/IndicatorTypes.py
otx_misp/otx/LICENSE
otx_misp/otx/OTXv2.py
otx_misp/otx/README.md
otx_misp/otx/__init__.py
otx_misp/otx/howto_use_python_otx_api.ipynb
otx_misp/otx/setup.py
otx_misp-1.1.dist-info/DESCRIPTION.rst
otx_misp-1.1.dist-info/METADATA
otx_misp-1.1.dist-info/RECORD
otx_misp-1.1.dist-info/WHEEL
otx_misp-1.1.dist-info/entry_points.txt
otx_misp-1.1.dist-info/metadata.json
otx_misp-1.1.dist-info/top_level.txt
