Metadata-Version: 2.0
Name: otx-misp
Version: 1.1
Summary: Imports Alienvault OTX pulses to a MISP instance.
Home-page: https://github.com/gcrahay/otx_misp
Author: Gaetan Crahay
Author-email: gaetan@crahay.eu
License: Apache 2.0
Keywords: Alienvault,OTX,MISP
Platform: UNKNOWN
Classifier: Development Status :: 5 - Production/Stable
Classifier: Intended Audience :: Developers
Classifier: License :: OSI Approved :: BSD License
Classifier: Operating System :: Unix
Classifier: Operating System :: POSIX
Classifier: Operating System :: Microsoft :: Windows
Classifier: Programming Language :: Python
Classifier: Programming Language :: Python :: 2.7
Classifier: Programming Language :: Python :: 3
Classifier: Programming Language :: Python :: 3.5
Classifier: Programming Language :: Python :: Implementation :: CPython
Classifier: Programming Language :: Python :: Implementation :: PyPy
Classifier: Topic :: Utilities
Requires-Dist: pymisp (>=2.4.53)
Requires-Dist: python-dateutil
